370lab2/DataMem.v
`timescale 1ns / 1ps
module DataMem (
    input [31:0] address,
    input [31:0] store_data,
    input mem_write,
    input mem_read,
    output reg [31:0] load_data);
    
    reg [31:0] data_memory [2^32 - 1:0];
    
    always@(address, store_data, mem_write, mem_read) begin
        if(mem_write && !mem_read)
            data_memory[address] <= store_data;
    end
    
    always@(address, mem_write, mem_read) begin
        if(mem_read && !mem_write)
            load_data <= data_memory[address];
        else load_data <= 0;
    end
    
endmodule

370lab2/wave.vcd
$version Generated by VerilatedVcd $end
$timescale 1ps $end
 $scope module TOP $end
  $var wire 32 A address [31:0] $end
  $var wire 32 B store_data [31:0] $end
  $var wire 1 C mem_write $end
  $var wire 1 D mem_read $end
  $var wire 32 E load_data [31:0] $end
  $scope module DataMem $end
   $var wire 32 A address [31:0] $end
   $var wire 32 B store_data [31:0] $end
   $var wire 1 C mem_write $end
   $var wire 1 D mem_read $end
   $var wire 32 E load_data [31:0] $end
   $var wire 32 # data_memory[0] [31:0] $end
   $var wire 32 $ data_memory[1] [31:0] $end
   $var wire 32 % data_memory[2] [31:0] $end
   $var wire 32 & data_memory[3] [31:0] $end
   $var wire 32 ' data_memory[4] [31:0] $end
   $var wire 32 ( data_memory[5] [31:0] $end
   $var wire 32 ) data_memory[6] [31:0] $end
   $var wire 32 * data_memory[7] [31:0] $end
   $var wire 32 + data_memory[8] [31:0] $end
   $var wire 32 , data_memory[9] [31:0] $end
   $var wire 32 - data_memory[10] [31:0] $end
   $var wire 32 . data_memory[11] [31:0] $end
   $var wire 32 / data_memory[12] [31:0] $end
   $var wire 32 0 data_memory[13] [31:0] $end
   $var wire 32 1 data_memory[14] [31:0] $end
   $var wire 32 2 data_memory[15] [31:0] $end
   $var wire 32 3 data_memory[16] [31:0] $end
   $var wire 32 4 data_memory[17] [31:0] $end
   $var wire 32 5 data_memory[18] [31:0] $end
   $var wire 32 6 data_memory[19] [31:0] $end
   $var wire 32 7 data_memory[20] [31:0] $end
   $var wire 32 8 data_memory[21] [31:0] $end
   $var wire 32 9 data_memory[22] [31:0] $end
   $var wire 32 : data_memory[23] [31:0] $end
   $var wire 32 ; data_memory[24] [31:0] $end
   $var wire 32 < data_memory[25] [31:0] $end
   $var wire 32 = data_memory[26] [31:0] $end
   $var wire 32 > data_memory[27] [31:0] $end
   $var wire 32 ? data_memory[28] [31:0] $end
   $var wire 32 @ data_memory[29] [31:0] $end
  $upscope $end
 $upscope $end
$enddefinitions $end


#0
b00000000000000000000000000000000 #
b00000000000000000000000000000000 $
b00000000000000000000000000000000 %
b00000000000000000000000000000000 &
b00000000000000000000000000000000 '
b00000000000000000000000000000000 (
b00000000000000000000000000000000 )
b00000000000000000000000000000000 *
b00000000000000000000000000000000 +
b00000000000000000000000000000000 ,
b00000000000000000000000000000000 -
b00000000000000000000000000000000 .
b00000000000000000000000000000000 /
b00000000000000000000000000000000 0
b00000000000000000000000000000000 1
b00000000000000000000000000000000 2
b00000000000000000000000000000000 3
b00000000000000000000000000000000 4
b00000000000000000000000000000000 5
b00000000000000000000000000000000 6
b00000000000000000000000000000000 7
b00000000000000000000000000000000 8
b00000000000000000000000000000000 9
b00000000000000000000000000000000 :
b00000000000000000000000000000000 ;
b00000000000000000000000000000000 <
b00000000000000000000000000000000 =
b00000000000000000000000000000000 >
b00000000000000000000000000000000 ?
b00000000000000000000000000000000 @
b00000000000000000000000000000011 A
b00110010011110110010001111000110 B
1C
1D
b00000000000000000000000000000000 E
#1
b00011001010010010101110011111111 B
0C
0D
#2
b00000000000000000000000000001001 A
b01000110111010000111110011001101 B
1D
#3
b01000001101101110001111011111011 #
b00000000000000000000000000000000 A
b01000001101101110001111011111011 B
1C
0D
#4
b01011011110100000110001011000010 B
0C
#5
b00000000000000000000000000000001 A
b00011111000101101110100111101000 B
1C
1D
#6
b00000000000000000000000000000010 A
b00110011010100100010010101011010 B
0C
#7
b00011011111011111101011110011111 *
b00000000000000000000000000000111 A
b00011011111011111101011110011111 B
1C
0D
#8
b00000000000000000000000000000010 A
b00100101111001000101110100110010 B
1D
#9
b01111100100000111110010001011000 &
b00000000000000000000000000000011 A
b01111100100000111110010001011000 B
0D
#10
b00000000000000000000000000001001 A
b01100010100011001000100101011101 B
1D
#11
b00000000000000000000000000000100 A
b00101101000111010101101011101001 B
0C
0D
#12
b01111001100000111000110010110010 (
b00000000000000000000000000000101 A
b01111001100000111000110010110010 B
1C
#13
b00000000000000000000000000000001 A
b01010100111001001001111010110100 B
0C
1D
#14
b00000000000000000000000000000010 A
b00000010100100000001110110000010 B
#15
b00000000000000000000000000000101 A
b01111100001111011011110100111101 B
b01111001100000111000110010110010 E
#16
b00000000000000000000000000000110 A
b01000101000101101101110111101001 B
b00000000000000000000000000000000 E
#17
b00000000000000000000000000000011 A
b01010101011101111111100011100001 B
b01111100100000111110010001011000 E
#18
b00000000000000000000000000000010 A
b01110111010001100101111100000001 B
b00000000000000000000000000000000 E
#19
b01011110100010000100101011011100 '
b00000000000000000000000000000100 A
b01011110100010000100101011011100 B
1C
0D
#20
b00000000000000000000000000000111 A
b00010101001111101010010000111000 B
0C
#21
b00000000000000000000000000001000 A
b00101010010010000111110010110000 B
1C
1D
#22
b00000000000000000000000000000100 A
b01010111111001001100110010101111 B
0C
0D
#23
b01101101111010010001101100011000 )
b00000000000000000000000000000110 A
b01101101111010010001101100011000 B
1C
#24
b01101000010010100100100000011010 B
0C
1D
b01101101111010010001101100011000 E
#25
b00000000000000000000000000000101 A
b00011011101000000010011011111010 B
0D
b00000000000000000000000000000000 E
#26
b01110000110001101010010100101001 *
b00000000000000000000000000000111 A
b01110000110001101010010100101001 B
1C
#27
b00100011111110011100000100111100 B
0C
#28
b00000000000000000000000000000001 A
b00011100111100010000111111011000 B
1D
#29
b00000000000000000000000000000101 A
b00110101010011111110100111111001 B
b01111001100000111000110010110010 E
#30
b00000000000000000000000000000000 A
b00010000001000110011110010011001 B
1C
b00000000000000000000000000000000 E
#31
b00000000000000000000000000000111 A
b01110111101011100011010111101011 B
#32
b00101111001100000101110111101111 ,
b00000000000000000000000000001001 A
b00101111001100000101110111101111 B
0D
#33
b00000000000000000000000000000111 A
b00011111010010001110101010100001 B
0C
1D
b01110000110001101010010100101001 E
#34
b01100101100100000111000000001011 )
b00000000000000000000000000000110 A
b01100101100100000111000000001011 B
1C
0D
b00000000000000000000000000000000 E
#35
b00000000000000000000000000001000 A
b01111001100111010000001001000111 B
0C
1D
#36
b00000000000000000000000000000011 A
b00011110101110100101110100100011 B
0D
#37
b00000000000000000000000000001000 A
b01111011110100111110111001111011 B
1D
#38
b00000000000000000000000000000110 A
b00010001010001000111101101110011 B
b01100101100100000111000000001011 E
#39
b00011010001100100010001101001011 B
1C
b00000000000000000000000000000000 E
#40
b00000000000000000000000000001001 A
b01100000101101101101111101110000 B
0C
0D
#41
b00011010001001110111000010011110 $
b00000000000000000000000000000001 A
b00011010001001110111000010011110 B
1C
